WPDevEnvCreator/CommandLine.py
WPDevEnvCreator/DBDevEnvCreator.py
WPDevEnvCreator/DBUtility.py
WPDevEnvCreator/FileDevEnvCreator.py
WPDevEnvCreator/SSHUtility.py
WPDevEnvCreator/__init__.py
WPDevEnvCreator/Utils/Constants.py
WPDevEnvCreator/Utils/Logger.py
WPDevEnvCreator/Utils/__init__.py
WPDevEnvCreator-7.dist-info/DESCRIPTION.rst
WPDevEnvCreator-7.dist-info/METADATA
WPDevEnvCreator-7.dist-info/RECORD
WPDevEnvCreator-7.dist-info/WHEEL
WPDevEnvCreator-7.dist-info/entry_points.txt
WPDevEnvCreator-7.dist-info/metadata.json
WPDevEnvCreator-7.dist-info/top_level.txt
